{
  "BG_LAYERS": [],
  "COLLISION_LAYER": [
    {
      "name": "Solid",
      "type": "Solid",
      "xds": -640,
      "yds": 0,
      "region": [0, 0, 16, 16]
    },
    {
      "name": "UpDoor",
      "type": "Door",
      "xds": -624,
      "yds": 0,
      "region": [64, 0, 16, 16],
      "data": { "STAGE_NO": 0, "target": "gym_tall" }
    },
    {
      "name": "UpDoor",
      "type": "Door",
      "xds": -608,
      "yds": 0,
      "region": [64, 0, 16, 16],
      "data": { "STAGE_NO": 0, "target": "gym_tall" }
    },
    {
      "name": "UpDoor",
      "type": "Door",
      "xds": -592,
      "yds": 0,
      "region": [64, 0, 16, 16],
      "data": { "STAGE_NO": 0, "target": "gym_tall" }
    },
    {
      "name": "Solid",
      "type": "Solid",
      "xds": -576,
      "yds": 0,
      "region": [0, 0, 16, 16]
    },
    {
      "name": "Solid",
      "type": "Solid",
      "xds": -560,
      "yds": 0,
      "region": [0, 0, 16, 16]
    },
    {
      "name": "Solid",
      "type": "Solid",
      "xds": -544,
      "yds": 0,
      "region": [0, 0, 16, 16]
    },
    {
      "name": "Solid",
      "type": "Solid",
      "xds": -528,
      "yds": 0,
      "region": [0, 0, 16, 16]
    },
    {
      "name": "Solid",
      "type": "Solid",
      "xds": -512,
      "yds": 0,
      "region": [0, 0, 16, 16]
    },
    {
      "name": "Solid",
      "type": "Solid",
      "xds": -496,
      "yds": 0,
      "region": [0, 0, 16, 16]
    },
    {
      "name": "Solid",
      "type": "Solid",
      "xds": -480,
      "yds": 0,
      "region": [0, 0, 16, 16]
    },
    {
      "name": "Solid",
      "type": "Solid",
      "xds": -464,
      "yds": 0,
      "region": [0, 0, 16, 16]
    },
    {
      "name": "Solid",
      "type": "Solid",
      "xds": -448,
      "yds": 0,
      "region": [0, 0, 16, 16]
    },
    {
      "name": "Solid",
      "type": "Solid",
      "xds": -432,
      "yds": 0,
      "region": [0, 0, 16, 16]
    },
    {
      "name": "Solid",
      "type": "Solid",
      "xds": -416,
      "yds": 0,
      "region": [0, 0, 16, 16]
    },
    {
      "name": "Solid",
      "type": "Solid",
      "xds": -400,
      "yds": 0,
      "region": [0, 0, 16, 16]
    },
    {
      "name": "Solid",
      "type": "Solid",
      "xds": -384,
      "yds": 0,
      "region": [0, 0, 16, 16]
    },
    {
      "name": "Solid",
      "type": "Solid",
      "xds": -368,
      "yds": 0,
      "region": [0, 0, 16, 16]
    },
    {
      "name": "Solid",
      "type": "Solid",
      "xds": -352,
      "yds": 0,
      "region": [0, 0, 16, 16]
    },
    {
      "name": "Solid",
      "type": "Solid",
      "xds": -336,
      "yds": 0,
      "region": [0, 0, 16, 16]
    },
    {
      "name": "Solid",
      "type": "Solid",
      "xds": -320,
      "yds": 0,
      "region": [0, 0, 16, 16]
    },
    {
      "name": "Solid",
      "type": "Solid",
      "xds": -304,
      "yds": 0,
      "region": [0, 0, 16, 16]
    },
    {
      "name": "Solid",
      "type": "Solid",
      "xds": -288,
      "yds": 0,
      "region": [0, 0, 16, 16]
    },
    {
      "name": "Solid",
      "type": "Solid",
      "xds": -272,
      "yds": 0,
      "region": [0, 0, 16, 16]
    },
    {
      "name": "Solid",
      "type": "Solid",
      "xds": -256,
      "yds": 0,
      "region": [0, 0, 16, 16]
    },
    {
      "name": "Solid",
      "type": "Solid",
      "xds": -240,
      "yds": 0,
      "region": [0, 0, 16, 16]
    },
    {
      "name": "Solid",
      "type": "Solid",
      "xds": -224,
      "yds": 0,
      "region": [0, 0, 16, 16]
    },
    {
      "name": "Solid",
      "type": "Solid",
      "xds": -208,
      "yds": 0,
      "region": [0, 0, 16, 16]
    },
    {
      "name": "Solid",
      "type": "Solid",
      "xds": -192,
      "yds": 0,
      "region": [0, 0, 16, 16]
    },
    {
      "name": "Solid",
      "type": "Solid",
      "xds": -176,
      "yds": 0,
      "region": [0, 0, 16, 16]
    },
    {
      "name": "Solid",
      "type": "Solid",
      "xds": -160,
      "yds": 0,
      "region": [0, 0, 16, 16]
    },
    {
      "name": "Solid",
      "type": "Solid",
      "xds": -144,
      "yds": 0,
      "region": [0, 0, 16, 16]
    },
    {
      "name": "Solid",
      "type": "Solid",
      "xds": -128,
      "yds": 0,
      "region": [0, 0, 16, 16]
    },
    {
      "name": "Solid",
      "type": "Solid",
      "xds": -112,
      "yds": 0,
      "region": [0, 0, 16, 16]
    },
    {
      "name": "Solid",
      "type": "Solid",
      "xds": -96,
      "yds": 0,
      "region": [0, 0, 16, 16]
    },
    {
      "name": "Solid",
      "type": "Solid",
      "xds": -80,
      "yds": 0,
      "region": [0, 0, 16, 16]
    },
    {
      "name": "Solid",
      "type": "Solid",
      "xds": -64,
      "yds": 0,
      "region": [0, 0, 16, 16]
    },
    {
      "name": "Solid",
      "type": "Solid",
      "xds": -48,
      "yds": 0,
      "region": [0, 0, 16, 16]
    },
    {
      "name": "Solid",
      "type": "Solid",
      "xds": -32,
      "yds": 0,
      "region": [0, 0, 16, 16]
    },
    {
      "name": "Solid",
      "type": "Solid",
      "xds": -16,
      "yds": 0,
      "region": [0, 0, 16, 16]
    },
    {
      "name": "Solid",
      "type": "Solid",
      "xds": -640,
      "yds": 16,
      "region": [0, 0, 16, 16]
    },
    0,
    0,
    0,
    {
      "name": "Solid",
      "type": "Solid",
      "xds": -576,
      "yds": 16,
      "region": [0, 0, 16, 16]
    },
    {
      "name": "Solid",
      "type": "Solid",
      "xds": -560,
      "yds": 16,
      "region": [0, 0, 16, 16]
    },
    {
      "name": "Solid",
      "type": "Solid",
      "xds": -544,
      "yds": 16,
      "region": [0, 0, 16, 16]
    },
    {
      "name": "Solid",
      "type": "Solid",
      "xds": -528,
      "yds": 16,
      "region": [0, 0, 16, 16]
    },
    {
      "name": "Solid",
      "type": "Solid",
      "xds": -512,
      "yds": 16,
      "region": [0, 0, 16, 16]
    },
    {
      "name": "Solid",
      "type": "Solid",
      "xds": -496,
      "yds": 16,
      "region": [0, 0, 16, 16]
    },
    {
      "name": "Solid",
      "type": "Solid",
      "xds": -480,
      "yds": 16,
      "region": [0, 0, 16, 16]
    },
    {
      "name": "Solid",
      "type": "Solid",
      "xds": -464,
      "yds": 16,
      "region": [0, 0, 16, 16]
    },
    {
      "name": "Solid",
      "type": "Solid",
      "xds": -448,
      "yds": 16,
      "region": [0, 0, 16, 16]
    },
    {
      "name": "Solid",
      "type": "Solid",
      "xds": -432,
      "yds": 16,
      "region": [0, 0, 16, 16]
    },
    {
      "name": "Solid",
      "type": "Solid",
      "xds": -416,
      "yds": 16,
      "region": [0, 0, 16, 16]
    },
    {
      "name": "Solid",
      "type": "Solid",
      "xds": -400,
      "yds": 16,
      "region": [0, 0, 16, 16]
    },
    {
      "name": "Solid",
      "type": "Solid",
      "xds": -384,
      "yds": 16,
      "region": [0, 0, 16, 16]
    },
    {
      "name": "Solid",
      "type": "Solid",
      "xds": -368,
      "yds": 16,
      "region": [0, 0, 16, 16]
    },
    {
      "name": "Solid",
      "type": "Solid",
      "xds": -352,
      "yds": 16,
      "region": [0, 0, 16, 16]
    },
    {
      "name": "Solid",
      "type": "Solid",
      "xds": -336,
      "yds": 16,
      "region": [0, 0, 16, 16]
    },
    {
      "name": "Solid",
      "type": "Solid",
      "xds": -320,
      "yds": 16,
      "region": [0, 0, 16, 16]
    },
    0,
    0,
    0,
    0,
    0,
    0,
    0,
    0,
    0,
    0,
    0,
    0,
    0,
    0,
    0,
    0,
    0,
    {
      "name": "Solid",
      "type": "Solid",
      "xds": -32,
      "yds": 16,
      "region": [0, 0, 16, 16]
    },
    {
      "name": "Solid",
      "type": "Solid",
      "xds": -16,
      "yds": 16,
      "region": [0, 0, 16, 16]
    },
    {
      "name": "Solid",
      "type": "Solid",
      "xds": -640,
      "yds": 32,
      "region": [0, 0, 16, 16]
    },
    0,
    0,
    0,
    0,
    0,
    0,
    0,
    0,
    0,
    0,
    0,
    0,
    0,
    0,
    0,
    0,
    0,
    0,
    0,
    0,
    0,
    0,
    0,
    0,
    0,
    0,
    0,
    0,
    0,
    0,
    0,
    0,
    0,
    0,
    0,
    0,
    0,
    {
      "name": "Solid",
      "type": "Solid",
      "xds": -32,
      "yds": 32,
      "region": [0, 0, 16, 16]
    },
    {
      "name": "Solid",
      "type": "Solid",
      "xds": -16,
      "yds": 32,
      "region": [0, 0, 16, 16]
    },
    {
      "name": "Solid",
      "type": "Solid",
      "xds": -640,
      "yds": 48,
      "region": [0, 0, 16, 16]
    },
    {
      "name": "Thin",
      "type": "Thin",
      "xds": -624,
      "yds": 48,
      "region": [16, 0, 16, 16]
    },
    {
      "name": "Thin",
      "type": "Thin",
      "xds": -608,
      "yds": 48,
      "region": [16, 0, 16, 16]
    },
    {
      "name": "Thin",
      "type": "Thin",
      "xds": -592,
      "yds": 48,
      "region": [16, 0, 16, 16]
    },
    0,
    0,
    0,
    0,
    0,
    0,
    0,
    0,
    0,
    0,
    0,
    0,
    0,
    0,
    0,
    0,
    0,
    0,
    0,
    0,
    0,
    0,
    0,
    0,
    0,
    0,
    0,
    0,
    0,
    0,
    0,
    0,
    0,
    0,
    {
      "name": "Solid",
      "type": "Solid",
      "xds": -32,
      "yds": 48,
      "region": [0, 0, 16, 16]
    },
    {
      "name": "Solid",
      "type": "Solid",
      "xds": -16,
      "yds": 48,
      "region": [0, 0, 16, 16]
    },
    {
      "name": "Solid",
      "type": "Solid",
      "xds": -640,
      "yds": 64,
      "region": [0, 0, 16, 16]
    },
    0,
    0,
    0,
    0,
    0,
    0,
    0,
    0,
    0,
    0,
    0,
    0,
    0,
    0,
    0,
    0,
    0,
    0,
    0,
    0,
    0,
    0,
    0,
    0,
    0,
    0,
    0,
    0,
    0,
    0,
    0,
    0,
    0,
    0,
    0,
    0,
    0,
    {
      "name": "Solid",
      "type": "Solid",
      "xds": -32,
      "yds": 64,
      "region": [0, 0, 16, 16]
    },
    {
      "name": "Solid",
      "type": "Solid",
      "xds": -16,
      "yds": 64,
      "region": [0, 0, 16, 16]
    },
    {
      "name": "Solid",
      "type": "Solid",
      "xds": -640,
      "yds": 80,
      "region": [0, 0, 16, 16]
    },
    0,
    0,
    0,
    0,
    0,
    0,
    0,
    0,
    0,
    0,
    0,
    0,
    0,
    0,
    0,
    0,
    0,
    0,
    0,
    0,
    0,
    0,
    0,
    0,
    0,
    0,
    0,
    0,
    0,
    0,
    0,
    0,
    0,
    0,
    0,
    0,
    0,
    {
      "name": "Solid",
      "type": "Solid",
      "xds": -32,
      "yds": 80,
      "region": [0, 0, 16, 16]
    },
    {
      "name": "Solid",
      "type": "Solid",
      "xds": -16,
      "yds": 80,
      "region": [0, 0, 16, 16]
    },
    {
      "name": "Solid",
      "type": "Solid",
      "xds": -640,
      "yds": 96,
      "region": [0, 0, 16, 16]
    },
    {
      "name": "Thin",
      "type": "Thin",
      "xds": -624,
      "yds": 96,
      "region": [16, 0, 16, 16]
    },
    {
      "name": "Thin",
      "type": "Thin",
      "xds": -608,
      "yds": 96,
      "region": [16, 0, 16, 16]
    },
    {
      "name": "Thin",
      "type": "Thin",
      "xds": -592,
      "yds": 96,
      "region": [16, 0, 16, 16]
    },
    0,
    0,
    0,
    0,
    0,
    0,
    0,
    0,
    0,
    0,
    0,
    0,
    0,
    0,
    0,
    0,
    0,
    0,
    0,
    0,
    0,
    0,
    0,
    0,
    0,
    0,
    0,
    0,
    0,
    0,
    0,
    0,
    0,
    0,
    0,
    {
      "name": "RightDoor",
      "type": "Door",
      "xds": -16,
      "yds": 96,
      "region": [48, 0, 16, 16],
      "data": { "STAGE_NO": 0, "target": "gym_small" }
    },
    {
      "name": "Solid",
      "type": "Solid",
      "xds": -640,
      "yds": 112,
      "region": [0, 0, 16, 16]
    },
    0,
    0,
    0,
    0,
    0,
    0,
    0,
    0,
    0,
    0,
    0,
    0,
    0,
    0,
    0,
    0,
    0,
    0,
    0,
    0,
    0,
    0,
    0,
    0,
    0,
    0,
    0,
    0,
    0,
    0,
    0,
    0,
    0,
    0,
    0,
    0,
    0,
    0,
    {
      "name": "RightDoor",
      "type": "Door",
      "xds": -16,
      "yds": 112,
      "region": [48, 0, 16, 16],
      "data": { "STAGE_NO": 0, "target": "gym_small" }
    },
    {
      "name": "Solid",
      "type": "Solid",
      "xds": -640,
      "yds": 128,
      "region": [0, 0, 16, 16]
    },
    0,
    0,
    0,
    0,
    0,
    0,
    0,
    0,
    0,
    0,
    0,
    0,
    0,
    0,
    0,
    0,
    0,
    0,
    {
      "name": "Solid",
      "type": "Solid",
      "xds": -336,
      "yds": 128,
      "region": [0, 0, 16, 16]
    },
    {
      "name": "Solid",
      "type": "Solid",
      "xds": -320,
      "yds": 128,
      "region": [0, 0, 16, 16]
    },
    0,
    0,
    0,
    0,
    0,
    0,
    0,
    0,
    0,
    0,
    0,
    0,
    0,
    0,
    0,
    0,
    0,
    0,
    {
      "name": "RightDoor",
      "type": "Door",
      "xds": -16,
      "yds": 128,
      "region": [48, 0, 16, 16],
      "data": { "STAGE_NO": 0, "target": "gym_small" }
    },
    {
      "name": "Solid",
      "type": "Solid",
      "xds": -640,
      "yds": 144,
      "region": [0, 0, 16, 16]
    },
    {
      "name": "Solid",
      "type": "Solid",
      "xds": -624,
      "yds": 144,
      "region": [0, 0, 16, 16]
    },
    {
      "name": "Solid",
      "type": "Solid",
      "xds": -608,
      "yds": 144,
      "region": [0, 0, 16, 16]
    },
    {
      "name": "Solid",
      "type": "Solid",
      "xds": -592,
      "yds": 144,
      "region": [0, 0, 16, 16]
    },
    {
      "name": "Solid",
      "type": "Solid",
      "xds": -576,
      "yds": 144,
      "region": [0, 0, 16, 16]
    },
    {
      "name": "Solid",
      "type": "Solid",
      "xds": -560,
      "yds": 144,
      "region": [0, 0, 16, 16]
    },
    {
      "name": "Solid",
      "type": "Solid",
      "xds": -544,
      "yds": 144,
      "region": [0, 0, 16, 16]
    },
    {
      "name": "Solid",
      "type": "Solid",
      "xds": -528,
      "yds": 144,
      "region": [0, 0, 16, 16]
    },
    {
      "name": "Solid",
      "type": "Solid",
      "xds": -512,
      "yds": 144,
      "region": [0, 0, 16, 16]
    },
    {
      "name": "Solid",
      "type": "Solid",
      "xds": -496,
      "yds": 144,
      "region": [0, 0, 16, 16]
    },
    {
      "name": "Solid",
      "type": "Solid",
      "xds": -480,
      "yds": 144,
      "region": [0, 0, 16, 16]
    },
    {
      "name": "Solid",
      "type": "Solid",
      "xds": -464,
      "yds": 144,
      "region": [0, 0, 16, 16]
    },
    {
      "name": "Solid",
      "type": "Solid",
      "xds": -448,
      "yds": 144,
      "region": [0, 0, 16, 16]
    },
    {
      "name": "Solid",
      "type": "Solid",
      "xds": -432,
      "yds": 144,
      "region": [0, 0, 16, 16]
    },
    {
      "name": "Solid",
      "type": "Solid",
      "xds": -416,
      "yds": 144,
      "region": [0, 0, 16, 16]
    },
    {
      "name": "Solid",
      "type": "Solid",
      "xds": -400,
      "yds": 144,
      "region": [0, 0, 16, 16]
    },
    {
      "name": "Solid",
      "type": "Solid",
      "xds": -384,
      "yds": 144,
      "region": [0, 0, 16, 16]
    },
    {
      "name": "Solid",
      "type": "Solid",
      "xds": -368,
      "yds": 144,
      "region": [0, 0, 16, 16]
    },
    {
      "name": "Solid",
      "type": "Solid",
      "xds": -352,
      "yds": 144,
      "region": [0, 0, 16, 16]
    },
    {
      "name": "Solid",
      "type": "Solid",
      "xds": -336,
      "yds": 144,
      "region": [0, 0, 16, 16]
    },
    {
      "name": "Solid",
      "type": "Solid",
      "xds": -320,
      "yds": 144,
      "region": [0, 0, 16, 16]
    },
    {
      "name": "Solid",
      "type": "Solid",
      "xds": -304,
      "yds": 144,
      "region": [0, 0, 16, 16]
    },
    {
      "name": "Solid",
      "type": "Solid",
      "xds": -288,
      "yds": 144,
      "region": [0, 0, 16, 16]
    },
    {
      "name": "Solid",
      "type": "Solid",
      "xds": -272,
      "yds": 144,
      "region": [0, 0, 16, 16]
    },
    {
      "name": "Solid",
      "type": "Solid",
      "xds": -256,
      "yds": 144,
      "region": [0, 0, 16, 16]
    },
    {
      "name": "Solid",
      "type": "Solid",
      "xds": -240,
      "yds": 144,
      "region": [0, 0, 16, 16]
    },
    {
      "name": "Solid",
      "type": "Solid",
      "xds": -224,
      "yds": 144,
      "region": [0, 0, 16, 16]
    },
    {
      "name": "Solid",
      "type": "Solid",
      "xds": -208,
      "yds": 144,
      "region": [0, 0, 16, 16]
    },
    {
      "name": "Solid",
      "type": "Solid",
      "xds": -192,
      "yds": 144,
      "region": [0, 0, 16, 16]
    },
    {
      "name": "Solid",
      "type": "Solid",
      "xds": -176,
      "yds": 144,
      "region": [0, 0, 16, 16]
    },
    {
      "name": "Solid",
      "type": "Solid",
      "xds": -160,
      "yds": 144,
      "region": [0, 0, 16, 16]
    },
    {
      "name": "Solid",
      "type": "Solid",
      "xds": -144,
      "yds": 144,
      "region": [0, 0, 16, 16]
    },
    {
      "name": "Solid",
      "type": "Solid",
      "xds": -128,
      "yds": 144,
      "region": [0, 0, 16, 16]
    },
    {
      "name": "Solid",
      "type": "Solid",
      "xds": -112,
      "yds": 144,
      "region": [0, 0, 16, 16]
    },
    {
      "name": "Solid",
      "type": "Solid",
      "xds": -96,
      "yds": 144,
      "region": [0, 0, 16, 16]
    },
    {
      "name": "Solid",
      "type": "Solid",
      "xds": -80,
      "yds": 144,
      "region": [0, 0, 16, 16]
    },
    {
      "name": "Solid",
      "type": "Solid",
      "xds": -64,
      "yds": 144,
      "region": [0, 0, 16, 16]
    },
    {
      "name": "Solid",
      "type": "Solid",
      "xds": -48,
      "yds": 144,
      "region": [0, 0, 16, 16]
    },
    {
      "name": "Solid",
      "type": "Solid",
      "xds": -32,
      "yds": 144,
      "region": [0, 0, 16, 16]
    },
    {
      "name": "Solid",
      "type": "Solid",
      "xds": -16,
      "yds": 144,
      "region": [0, 0, 16, 16]
    },
    {
      "name": "Solid",
      "type": "Solid",
      "xds": -640,
      "yds": 160,
      "region": [0, 0, 16, 16]
    },
    {
      "name": "Solid",
      "type": "Solid",
      "xds": -624,
      "yds": 160,
      "region": [0, 0, 16, 16]
    },
    {
      "name": "Solid",
      "type": "Solid",
      "xds": -608,
      "yds": 160,
      "region": [0, 0, 16, 16]
    },
    {
      "name": "Solid",
      "type": "Solid",
      "xds": -592,
      "yds": 160,
      "region": [0, 0, 16, 16]
    },
    {
      "name": "Solid",
      "type": "Solid",
      "xds": -576,
      "yds": 160,
      "region": [0, 0, 16, 16]
    },
    {
      "name": "Solid",
      "type": "Solid",
      "xds": -560,
      "yds": 160,
      "region": [0, 0, 16, 16]
    },
    {
      "name": "Solid",
      "type": "Solid",
      "xds": -544,
      "yds": 160,
      "region": [0, 0, 16, 16]
    },
    {
      "name": "Solid",
      "type": "Solid",
      "xds": -528,
      "yds": 160,
      "region": [0, 0, 16, 16]
    },
    {
      "name": "Solid",
      "type": "Solid",
      "xds": -512,
      "yds": 160,
      "region": [0, 0, 16, 16]
    },
    {
      "name": "Solid",
      "type": "Solid",
      "xds": -496,
      "yds": 160,
      "region": [0, 0, 16, 16]
    },
    {
      "name": "Solid",
      "type": "Solid",
      "xds": -480,
      "yds": 160,
      "region": [0, 0, 16, 16]
    },
    {
      "name": "Solid",
      "type": "Solid",
      "xds": -464,
      "yds": 160,
      "region": [0, 0, 16, 16]
    },
    {
      "name": "Solid",
      "type": "Solid",
      "xds": -448,
      "yds": 160,
      "region": [0, 0, 16, 16]
    },
    {
      "name": "Solid",
      "type": "Solid",
      "xds": -432,
      "yds": 160,
      "region": [0, 0, 16, 16]
    },
    {
      "name": "Solid",
      "type": "Solid",
      "xds": -416,
      "yds": 160,
      "region": [0, 0, 16, 16]
    },
    {
      "name": "Solid",
      "type": "Solid",
      "xds": -400,
      "yds": 160,
      "region": [0, 0, 16, 16]
    },
    {
      "name": "Solid",
      "type": "Solid",
      "xds": -384,
      "yds": 160,
      "region": [0, 0, 16, 16]
    },
    {
      "name": "Solid",
      "type": "Solid",
      "xds": -368,
      "yds": 160,
      "region": [0, 0, 16, 16]
    },
    {
      "name": "Solid",
      "type": "Solid",
      "xds": -352,
      "yds": 160,
      "region": [0, 0, 16, 16]
    },
    {
      "name": "Solid",
      "type": "Solid",
      "xds": -336,
      "yds": 160,
      "region": [0, 0, 16, 16]
    },
    {
      "name": "Solid",
      "type": "Solid",
      "xds": -320,
      "yds": 160,
      "region": [0, 0, 16, 16]
    },
    {
      "name": "Solid",
      "type": "Solid",
      "xds": -304,
      "yds": 160,
      "region": [0, 0, 16, 16]
    },
    {
      "name": "Solid",
      "type": "Solid",
      "xds": -288,
      "yds": 160,
      "region": [0, 0, 16, 16]
    },
    {
      "name": "Solid",
      "type": "Solid",
      "xds": -272,
      "yds": 160,
      "region": [0, 0, 16, 16]
    },
    {
      "name": "Solid",
      "type": "Solid",
      "xds": -256,
      "yds": 160,
      "region": [0, 0, 16, 16]
    },
    {
      "name": "Solid",
      "type": "Solid",
      "xds": -240,
      "yds": 160,
      "region": [0, 0, 16, 16]
    },
    {
      "name": "Solid",
      "type": "Solid",
      "xds": -224,
      "yds": 160,
      "region": [0, 0, 16, 16]
    },
    {
      "name": "Solid",
      "type": "Solid",
      "xds": -208,
      "yds": 160,
      "region": [0, 0, 16, 16]
    },
    {
      "name": "Solid",
      "type": "Solid",
      "xds": -192,
      "yds": 160,
      "region": [0, 0, 16, 16]
    },
    {
      "name": "Solid",
      "type": "Solid",
      "xds": -176,
      "yds": 160,
      "region": [0, 0, 16, 16]
    },
    {
      "name": "Solid",
      "type": "Solid",
      "xds": -160,
      "yds": 160,
      "region": [0, 0, 16, 16]
    },
    {
      "name": "Solid",
      "type": "Solid",
      "xds": -144,
      "yds": 160,
      "region": [0, 0, 16, 16]
    },
    {
      "name": "Solid",
      "type": "Solid",
      "xds": -128,
      "yds": 160,
      "region": [0, 0, 16, 16]
    },
    {
      "name": "Solid",
      "type": "Solid",
      "xds": -112,
      "yds": 160,
      "region": [0, 0, 16, 16]
    },
    {
      "name": "Solid",
      "type": "Solid",
      "xds": -96,
      "yds": 160,
      "region": [0, 0, 16, 16]
    },
    {
      "name": "Solid",
      "type": "Solid",
      "xds": -80,
      "yds": 160,
      "region": [0, 0, 16, 16]
    },
    {
      "name": "Solid",
      "type": "Solid",
      "xds": -64,
      "yds": 160,
      "region": [0, 0, 16, 16]
    },
    {
      "name": "Solid",
      "type": "Solid",
      "xds": -48,
      "yds": 160,
      "region": [0, 0, 16, 16]
    },
    {
      "name": "Solid",
      "type": "Solid",
      "xds": -32,
      "yds": 160,
      "region": [0, 0, 16, 16]
    },
    {
      "name": "Solid",
      "type": "Solid",
      "xds": -16,
      "yds": 160,
      "region": [0, 0, 16, 16]
    }
  ],
  "FG_LAYERS": [],
  "ROOM_RECT": [-640, 0, 640, 176],
  "SPRITE_SHEET_PNG_NAME": "stage_0_sprite_sheet.png",
  "TILE_S": 16,
  "BG1": "",
  "BG2": "",
  "BG3": "",
  "BG4": ""
}
